Lab practice/max2/max2.v
module second_largest #(parameter N = 32) (
	input clk, reset, 
	input [31:0] d_in,
	output reg [31:0] d_out
	);
	
	reg [31:0]  max1, max2;
	
	always @(posedge clk or negedge reset) begin
		if (!reset) begin
			max1 <= 0;
			max2 <= 0;
			d_out <= 0;
		end else begin
			if (d_in > max1) begin
				max2 <= max1;
				max1 <= d_in;
				d_out <= max1;
			end else if (d_in > max2) begin
				max2 <= d_in;
				d_out <= d_in;
			end else begin
				d_out <= max2;
			end
		end
	end
endmodule

Lab practice/max2/tb_max2.v
`timescale 1ns/1ns

module tb_second_largest;

	reg clk, reset;
	reg  [31:0] d_in;
	wire [31:0] d_out;

	second_largest dut(
		.clk(clk),
		.reset(reset),
		.d_in(d_in),
		.d_out(d_out)
	);

	initial begin
		clk = 0;
		forever #5 clk = ~clk;   // 10ns period
	end
	
	
	initial begin
		reset = 0; d_in = 0;
		#12;
		reset = 1;


		d_in = 5;   #10;
		d_in = 1;   #10;
		d_in = 10;  #10;
		d_in = 7;   #10;
		d_in = 10;  #10;   // repeated max
		d_in = 3;   #10;
		#20;
		$finish;
	end
	
	initial begin
		$display("Time | reset | d_in | d_out");
		$monitor("%0t	|  %b 	|	%0d	|  %0d", $time, reset, d_in, d_out);
  	end
  	
	initial begin
	  	$dumpfile("waveform.vcd");
	  	$dumpvars(0, tb_second_largest);
	end

endmodule

Lab practice/max2/waveform.vcd
$date
	Mon Nov 24 22:08:12 2025
$end
$version
	Icarus Verilog
$end
$timescale
	1ns
$end
$scope module tb_second_largest $end
$var wire 32 ! d_out [31:0] $end
$var reg 1 " clk $end
$var reg 32 # d_in [31:0] $end
$var reg 1 $ reset $end
$scope module dut $end
$var wire 1 " clk $end
$var wire 32 % d_in [31:0] $end
$var wire 1 $ reset $end
$var parameter 32 & N $end
$var reg 32 ' d_out [31:0] $end
$var reg 32 ( max1 [31:0] $end
$var reg 32 ) max2 [31:0] $end
$upscope $end
$upscope $end
$enddefinitions $end
$comment Show the parameter values. $end
$dumpall
b100000 &
$end
#0
$dumpvars
b0 )
b0 (
b0 '
b0 %
0$
b0 #
0"
b0 !
$end
#5
1"
#10
0"
#12
b101 #
b101 %
1$
#15
b101 !
b101 '
b101 (
1"
#20
0"
#22
b1 #
b1 %
#25
b1 )
1"
#30
0"
#32
b1010 #
b1010 %
#35
b1010 !
b1010 '
b1010 (
b101 )
1"
#40
0"
#42
b111 #
b111 %
#45
b111 )
1"
#50
0"
#52
b1010 #
b1010 %
#55
b1010 )
1"
#60
0"
#62
b11 #
b11 %
