Lab 2/SyncCounter.v
module SyncCounter #(parameter X=5)(input clk, input enable, input reset, input mode, output reg[2:0] count_out);

wire[2:0] reg_out;

assign reg_out = reset ? X : (mode ? (enable ? count_out+1 : count_out) : (enable ? count_out-1 : count_out));

always @(posedge clk) begin
	count_out <= reg_out;
end
endmodule

Lab 2/fsm_3lights.v
module TrafficState #(parameter X=6, parameter Y=5, parameter Z=3)(
    input  clk,
    input  reset,
    output reg [2:0] counter,         // active counter value
    output reg [1:0] traffic_state    // current traffic state
);

reg[1:0] curr_state, next_state;

parameter s0 = 2'b00;   // H_R
parameter s1 = 2'b01;   // H_Y -> Red to green
parameter s2 = 2'b10;   // H_G
parameter s3 = 2'b11;   // H_Y -> Green to red


wire[2:0] countX, countY, countZ_RG, countZ_GR;

SyncCounter #(X) counterX (
        .clk(clk),
        .enable(1'b1),
        .reset(reset | (curr_state != s0 && next_state == s0)),
        .mode(1'b0),
        .count_out(countX)
    );

SyncCounter #(Z) counterZ_RG (
		.clk(clk),
		.enable(1'b1),
		.reset(reset | (curr_state != s1 && next_state == s1)),
		.mode(1'b0),
		.count_out(countZ_RG)
	);

SyncCounter #(Y) counterY (
		.clk(clk),
		.enable(1'b1),
		.reset(reset | (curr_state != s2 && next_state == s2)),
		.mode(1'b0),
		.count_out(countY)
	);

SyncCounter #(Z) counterZ_GR (
		.clk(clk),
		.enable(1'b1),
		.reset(reset | (curr_state != s3 && next_state == s3)),
		.mode(1'b0),
		.count_out(countZ_GR)
	);


always @(posedge clk)
	if(reset)
		curr_state <= s0;
	else
		curr_state <= next_state;

always @(*) begin
	next_state = curr_state;
	case(curr_state)
		s0: begin 
		if(countX == 0)
			next_state = s1;        // go to yellow after Highway red
		end
		s1: begin
		if(countZ_RG == 0)
			next_state = s2;        // after yello, go to Highway green
		end
        s2: begin
		if(countY == 0)
			next_state = s3;        // go back to ywllow after Highway green
		end
        s3: begin
		if(countZ_GR == 0)
			next_state = s0;        // when yello from green ends, go back to Highway red
		end
	endcase
end

always @(*) begin
	traffic_state = curr_state;
	case(curr_state)
	s0: counter = countX;
	s1: counter = countZ_RG;
    s2: counter = countY;
    s3: counter = countZ_GR;
	endcase
end

endmodule

Lab 2/trafficlights_tb.v
module synccount_tb;

    reg clk;
    reg reset;
    wire [2:0] count;
    wire [1:0] trafficstate;

    initial clk = 0;
    always #5 clk = ~clk;

    TrafficState #(.X(6), .Y(4), .Z(3)) uut (
        .clk(clk),
        .reset(reset),
        .counter(count),
        .traffic_state(trafficstate)
    );

    initial begin
        reset = 1;
        #20;
        reset = 0;
        #500;
        reset = 1;
        #10;
        reset = 0;
        #300;
        $finish;
    end

    always @(trafficstate) begin
    case (trafficstate)
        2'b00: $display("Highway Red");
        2'b01: $display("Highway red -> Yellow");
        2'b10: $display("Highway GREEN");
        2'b11: $display("Highway Green -> yellow");
    endcase
    end

    initial begin
        $monitor("Time=%0t | reset=%b | counter=%d | state=%b", $time, reset, count, trafficstate);
    end

    initial begin
        $dumpfile("synccount_tb.vcd");
        $dumpvars(0, synccount_tb);
    end

endmodule

Lab 2/synccount_tb.vcd
$date
	Wed Sep 24 00:51:32 2025
$end
$version
	Icarus Verilog
$end
$timescale
	1s
$end
$scope module synccount_tb $end
$var wire 2 ! trafficstate [1:0] $end
$var wire 3 " count [2:0] $end
$var reg 1 # clk $end
$var reg 1 $ reset $end
$scope module uut $end
$var wire 1 # clk $end
$var wire 1 $ reset $end
$var wire 3 % countZ_RG [2:0] $end
$var wire 3 & countZ_GR [2:0] $end
$var wire 3 ' countY [2:0] $end
$var wire 3 ( countX [2:0] $end
$var parameter 32 ) X $end
$var parameter 32 * Y $end
$var parameter 32 + Z $end
$var parameter 2 , s0 $end
$var parameter 2 - s1 $end
$var parameter 2 . s2 $end
$var parameter 2 / s3 $end
$var reg 3 0 counter [2:0] $end
$var reg 2 1 curr_state [1:0] $end
$var reg 2 2 next_state [1:0] $end
$var reg 2 3 traffic_state [1:0] $end
$scope module counterX $end
$var wire 1 # clk $end
$var wire 1 4 enable $end
$var wire 1 5 mode $end
$var wire 1 6 reset $end
$var wire 3 7 reg_out [2:0] $end
$var parameter 32 8 X $end
$var reg 3 9 count_out [2:0] $end
$upscope $end
$scope module counterY $end
$var wire 1 # clk $end
$var wire 1 : enable $end
$var wire 1 ; mode $end
$var wire 1 < reset $end
$var wire 3 = reg_out [2:0] $end
$var parameter 32 > X $end
$var reg 3 ? count_out [2:0] $end
$upscope $end
$scope module counterZ_GR $end
$var wire 1 # clk $end
$var wire 1 @ enable $end
$var wire 1 A mode $end
$var wire 1 B reset $end
$var wire 3 C reg_out [2:0] $end
$var parameter 32 D X $end
$var reg 3 E count_out [2:0] $end
$upscope $end
$scope module counterZ_RG $end
$var wire 1 # clk $end
$var wire 1 F enable $end
$var wire 1 G mode $end
$var wire 1 H reset $end
$var wire 3 I reg_out [2:0] $end
$var parameter 32 J X $end
$var reg 3 K count_out [2:0] $end
$upscope $end
$upscope $end
$upscope $end
$enddefinitions $end
$comment Show the parameter values. $end
$dumpall
b11 J
b11 D
b100 >
b110 8
b11 /
b10 .
b1 -
b0 ,
b11 +
b100 *
b110 )
$end
#0
$dumpvars
bx K
b11 I
1H
0G
1F
bx E
b11 C
1B
0A
1@
bx ?
b100 =
1<
0;
1:
bx 9
b110 7
16
05
14
bx 3
bx 2
bx 1
bx 0
bx (
bx '
bx &
bx %
1$
0#
bx "
bx !
$end
#5
b110 "
b110 0
b0 !
b0 3
b0 2
b110 (
b110 9
b11 %
b11 K
b100 '
b100 ?
b11 &
b11 E
b0 1
1#
#10
0#
#15
1#
#20
b101 7
b10 I
b11 =
b10 C
06
0H
0<
0B
0#
0$
#25
b100 7
b1 I
b10 =
b1 C
b101 "
b101 0
b101 (
b101 9
b10 %
b10 K
b11 '
b11 ?
b10 &
b10 E
1#
#30
0#
#35
b0 C
b1 =
b0 I
b11 7
b100 "
b100 0
b1 &
b1 E
b10 '
b10 ?
b1 %
b1 K
b100 (
b100 9
1#
#40
0#
#45
b10 7
b111 I
b0 =
b111 C
b11 "
b11 0
b11 (
b11 9
b0 %
b0 K
b1 '
b1 ?
b0 &
b0 E
1#
#50
0#
#55
b110 C
b111 =
b110 I
b1 7
b10 "
b10 0
b111 &
b111 E
b0 '
b0 ?
b111 %
b111 K
b10 (
b10 9
1#
#60
0#
#65
b0 7
b101 I
b110 =
b101 C
b1 "
b1 0
b1 (
b1 9
b110 %
b110 K
b111 '
b111 ?
b110 &
b110 E
1#
#70
0#
#75
1H
b100 C
b101 =
b11 I
b111 7
b0 "
b0 0
b1 2
b101 &
b101 E
b110 '
b110 ?
b101 %
b101 K
b0 (
b0 9
1#
#80
0#
#85
b10 I
b110 7
b100 =
b11 C
0H
b11 "
b11 0
b1 !
b1 3
b111 (
b111 9
b11 %
b11 K
b101 '
b101 ?
b100 &
b100 E
b1 1
1#
#90
0#
#95
b10 C
b11 =
b1 I
b101 7
b10 "
b10 0
b11 &
b11 E
b100 '
b100 ?
b10 %
b10 K
b110 (
b110 9
1#
#100
0#
#105
b100 7
b0 I
b10 =
b1 C
b1 "
b1 0
b101 (
b101 9
b1 %
b1 K
b11 '
b11 ?
b10 &
b10 E
1#
#110
0#
#115
1<
b0 C
b100 =
b111 I
b11 7
b0 "
b0 0
b10 2
b1 &
b1 E
b10 '
b10 ?
b0 %
b0 K
b100 (
b100 9
1#
#120
0#
#125
b11 =
b10 7
b110 I
b111 C
0<
b100 "
b100 0
b10 !
b10 3
b11 (
b11 9
b111 %
b111 K
b100 '
b100 ?
b0 &
b0 E
b10 1
1#
#130
0#
#135
b110 C
b10 =
b101 I
b1 7
b11 "
b11 0
b111 &
b111 E
b11 '
b11 ?
b110 %
b110 K
b10 (
b10 9
1#
#140
0#
#145
b0 7
b100 I
b1 =
b101 C
b10 "
b10 0
b1 (
b1 9
b101 %
b101 K
b10 '
b10 ?
b110 &
b110 E
1#
#150
0#
#155
b100 C
b0 =
b11 I
b111 7
b1 "
b1 0
b101 &
b101 E
b1 '
b1 ?
b100 %
b100 K
b0 (
b0 9
1#
#160
0#
#165
1B
b110 7
b10 I
b111 =
b11 C
b11 2
b0 "
b0 0
b111 (
b111 9
b11 %
b11 K
b0 '
b0 ?
b100 &
b100 E
1#
#170
0#
#175
b10 C
0B
b110 =
b1 I
b101 7
b11 "
b11 0
b11 !
b11 3
b11 1
b11 &
b11 E
b111 '
b111 ?
b10 %
b10 K
b110 (
b110 9
1#
#180
0#
#185
b100 7
b0 I
b101 =
b1 C
b10 "
b10 0
b101 (
b101 9
b1 %
b1 K
b110 '
b110 ?
b10 &
b10 E
1#
#190
0#
#195
b0 C
b100 =
b111 I
b11 7
b1 "
b1 0
b1 &
b1 E
b101 '
b101 ?
b0 %
b0 K
b100 (
b100 9
1#
#200
0#
#205
16
b110 7
b110 I
b11 =
b111 C
b0 2
b0 "
b0 0
b11 (
b11 9
b111 %
b111 K
b100 '
b100 ?
b0 &
b0 E
1#
#210
0#
#215
b101 7
06
b110 C
b10 =
b101 I
b110 "
b110 0
b0 !
b0 3
b0 1
b111 &
b111 E
b11 '
b11 ?
b110 %
b110 K
b110 (
b110 9
1#
#220
0#
#225
b100 7
b100 I
b1 =
b101 C
b101 "
b101 0
b101 (
b101 9
b101 %
b101 K
b10 '
b10 ?
b110 &
b110 E
1#
#230
0#
#235
b100 C
b0 =
b11 I
b11 7
b100 "
b100 0
b101 &
b101 E
b1 '
b1 ?
b100 %
b100 K
b100 (
b100 9
1#
#240
0#
#245
b10 7
b10 I
b111 =
b11 C
b11 "
b11 0
b11 (
b11 9
b11 %
b11 K
b0 '
b0 ?
b100 &
b100 E
1#
#250
0#
#255
b10 C
b110 =
b1 I
b1 7
b10 "
b10 0
b11 &
b11 E
b111 '
b111 ?
b10 %
b10 K
b10 (
b10 9
1#
#260
0#
#265
b0 7
b0 I
b101 =
b1 C
b1 "
b1 0
b1 (
b1 9
b1 %
b1 K
b110 '
b110 ?
b10 &
b10 E
1#
#270
0#
#275
1H
b0 C
b100 =
b11 I
b111 7
b0 "
b0 0
b1 2
b1 &
b1 E
b101 '
b101 ?
b0 %
b0 K
b0 (
b0 9
1#
#280
0#
#285
b10 I
b110 7
b11 =
b111 C
0H
b11 "
b11 0
b1 !
b1 3
b111 (
b111 9
b11 %
b11 K
b100 '
b100 ?
b0 &
b0 E
b1 1
1#
#290
0#
#295
b110 C
b10 =
b1 I
b101 7
b10 "
b10 0
b111 &
b111 E
b11 '
b11 ?
b10 %
b10 K
b110 (
b110 9
1#
#300
0#
#305
b100 7
b0 I
b1 =
b101 C
b1 "
b1 0
b101 (
b101 9
b1 %
b1 K
b10 '
b10 ?
b110 &
b110 E
1#
#310
0#
#315
1<
b100 C
b100 =
b111 I
b11 7
b0 "
b0 0
b10 2
b101 &
b101 E
b1 '
b1 ?
b0 %
b0 K
b100 (
b100 9
1#
#320
0#
#325
b11 =
b10 7
b110 I
b11 C
0<
b100 "
b100 0
b10 !
b10 3
b11 (
b11 9
b111 %
b111 K
b100 '
b100 ?
b100 &
b100 E
b10 1
1#
#330
0#
#335
b10 C
b10 =
b101 I
b1 7
b11 "
b11 0
b11 &
b11 E
b11 '
b11 ?
b110 %
b110 K
b10 (
b10 9
1#
#340
0#
#345
b0 7
b100 I
b1 =
b1 C
b10 "
b10 0
b1 (
b1 9
b101 %
b101 K
b10 '
b10 ?
b10 &
b10 E
1#
#350
0#
#355
b0 C
b0 =
b11 I
b111 7
b1 "
b1 0
b1 &
b1 E
b1 '
b1 ?
b100 %
b100 K
b0 (
b0 9
1#
#360
0#
#365
1B
b110 7
b10 I
b111 =
b11 C
b11 2
b0 "
b0 0
b111 (
b111 9
b11 %
b11 K
b0 '
b0 ?
b0 &
b0 E
1#
#370
0#
#375
b10 C
0B
b110 =
b1 I
b101 7
b11 "
b11 0
b11 !
b11 3
b11 1
b11 &
b11 E
b111 '
b111 ?
b10 %
b10 K
b110 (
b110 9
1#
#380
0#
#385
b100 7
b0 I
b101 =
b1 C
b10 "
b10 0
b101 (
b101 9
b1 %
b1 K
b110 '
b110 ?
b10 &
b10 E
1#
#390
0#
#395
b0 C
b100 =
b111 I
b11 7
b1 "
b1 0
b1 &
b1 E
b101 '
b101 ?
b0 %
b0 K
b100 (
b100 9
1#
#400
0#
#405
16
b110 7
b110 I
b11 =
b111 C
b0 2
b0 "
b0 0
b11 (
b11 9
b111 %
b111 K
b100 '
b100 ?
b0 &
b0 E
1#
#410
0#
#415
b101 7
06
b110 C
b10 =
b101 I
b110 "
b110 0
b0 !
b0 3
b0 1
b111 &
b111 E
b11 '
b11 ?
b110 %
b110 K
b110 (
b110 9
1#
#420
0#
#425
b100 7
b100 I
b1 =
b101 C
b101 "
b101 0
b101 (
b101 9
b101 %
b101 K
b10 '
b10 ?
b110 &
b110 E
1#
#430
0#
#435
b100 C
b0 =
b11 I
b11 7
b100 "
b100 0
b101 &
b101 E
b1 '
b1 ?
b100 %
b100 K
b100 (
b100 9
1#
#440
0#
#445
b10 7
b10 I
b111 =
b11 C
b11 "
b11 0
b11 (
b11 9
b11 %
b11 K
b0 '
b0 ?
b100 &
b100 E
1#
#450
0#
#455
b10 C
b110 =
b1 I
b1 7
b10 "
b10 0
b11 &
b11 E
b111 '
b111 ?
b10 %
b10 K
b10 (
b10 9
1#
#460
0#
#465
b0 7
b0 I
b101 =
b1 C
b1 "
b1 0
b1 (
b1 9
b1 %
b1 K
b110 '
b110 ?
b10 &
b10 E
1#
#470
0#
#475
1H
b0 C
b100 =
b11 I
b111 7
b0 "
b0 0
b1 2
b1 &
b1 E
b101 '
b101 ?
b0 %
b0 K
b0 (
b0 9
1#
#480
0#
#485
b10 I
b110 7
b11 =
b111 C
0H
b11 "
b11 0
b1 !
b1 3
b111 (
b111 9
b11 %
b11 K
b100 '
b100 ?
b0 &
b0 E
b1 1
1#
#490
0#
#495
b110 C
b10 =
b1 I
b101 7
b10 "
b10 0
b111 &
b111 E
b11 '
b11 ?
b10 %
b10 K
b110 (
b110 9
1#
#500
0#
#505
b100 7
b0 I
b1 =
b101 C
b1 "
b1 0
b101 (
b101 9
b1 %
b1 K
b10 '
b10 ?
b110 &
b110 E
1#
#510
0#
#515
1<
b100 C
b100 =
b111 I
b11 7
b0 "
b0 0
b10 2
b101 &
b101 E
b1 '
b1 ?
b0 %
b0 K
b100 (
b100 9
1#
#520
b110 7
b11 I
b11 C
16
1H
1B
0#
1$
#525
b0 2
b110 "
b110 0
b0 !
b0 3
b110 (
b110 9
b11 %
b11 K
b100 '
b100 ?
b11 &
b11 E
b0 1
1#
#530
b101 7
b10 I
b11 =
b10 C
06
0H
0<
0B
0#
0$
#535
b1 C
b10 =
b1 I
b100 7
b101 "
b101 0
b10 &
b10 E
b11 '
b11 ?
b10 %
b10 K
b101 (
b101 9
1#
#540
0#
#545
b11 7
b0 I
b1 =
b0 C
b100 "
b100 0
b100 (
b100 9
b1 %
b1 K
b10 '
b10 ?
b1 &
b1 E
1#
#550
0#
#555
b111 C
b0 =
b111 I
b10 7
b11 "
b11 0
b0 &
b0 E
b1 '
b1 ?
b0 %
b0 K
b11 (
b11 9
1#
#560
0#
#565
b1 7
b110 I
b111 =
b110 C
b10 "
b10 0
b10 (
b10 9
b111 %
b111 K
b0 '
b0 ?
b111 &
b111 E
1#
#570
0#
#575
b101 C
b110 =
b101 I
b0 7
b1 "
b1 0
b110 &
b110 E
b111 '
b111 ?
b110 %
b110 K
b1 (
b1 9
1#
#580
0#
#585
1H
b111 7
b11 I
b101 =
b100 C
b1 2
b0 "
b0 0
b0 (
b0 9
b101 %
b101 K
b110 '
b110 ?
b101 &
b101 E
1#
#590
0#
#595
b10 I
0H
b11 C
b100 =
b110 7
b11 "
b11 0
b1 !
b1 3
b1 1
b100 &
b100 E
b101 '
b101 ?
b11 %
b11 K
b111 (
b111 9
1#
#600
0#
#605
b101 7
b1 I
b11 =
b10 C
b10 "
b10 0
b110 (
b110 9
b10 %
b10 K
b100 '
b100 ?
b11 &
b11 E
1#
#610
0#
#615
b1 C
b10 =
b0 I
b100 7
b1 "
b1 0
b10 &
b10 E
b11 '
b11 ?
b1 %
b1 K
b101 (
b101 9
1#
#620
0#
#625
1<
b11 7
b111 I
b100 =
b0 C
b10 2
b0 "
b0 0
b100 (
b100 9
b0 %
b0 K
b10 '
b10 ?
b1 &
b1 E
1#
#630
0#
#635
b11 =
0<
b111 C
b110 I
b10 7
b100 "
b100 0
b10 !
b10 3
b10 1
b0 &
b0 E
b100 '
b100 ?
b111 %
b111 K
b11 (
b11 9
1#
#640
0#
#645
b1 7
b101 I
b10 =
b110 C
b11 "
b11 0
b10 (
b10 9
b110 %
b110 K
b11 '
b11 ?
b111 &
b111 E
1#
#650
0#
#655
b101 C
b1 =
b100 I
b0 7
b10 "
b10 0
b110 &
b110 E
b10 '
b10 ?
b101 %
b101 K
b1 (
b1 9
1#
#660
0#
#665
b111 7
b11 I
b0 =
b100 C
b1 "
b1 0
b0 (
b0 9
b100 %
b100 K
b1 '
b1 ?
b101 &
b101 E
1#
#670
0#
#675
1B
b11 C
b111 =
b10 I
b110 7
b0 "
b0 0
b11 2
b100 &
b100 E
b0 '
b0 ?
b11 %
b11 K
b111 (
b111 9
1#
#680
0#
#685
b10 C
b101 7
b1 I
b110 =
0B
b11 "
b11 0
b11 !
b11 3
b110 (
b110 9
b10 %
b10 K
b111 '
b111 ?
b11 &
b11 E
b11 1
1#
#690
0#
#695
b1 C
b101 =
b0 I
b100 7
b10 "
b10 0
b10 &
b10 E
b110 '
b110 ?
b1 %
b1 K
b101 (
b101 9
1#
#700
0#
#705
b11 7
b111 I
b100 =
b0 C
b1 "
b1 0
b100 (
b100 9
b0 %
b0 K
b101 '
b101 ?
b1 &
b1 E
1#
#710
0#
#715
16
b111 C
b11 =
b110 I
b110 7
b0 "
b0 0
b0 2
b0 &
b0 E
b100 '
b100 ?
b111 %
b111 K
b11 (
b11 9
1#
#720
0#
#725
b101 7
b101 I
b10 =
b110 C
06
b110 "
b110 0
b0 !
b0 3
b110 (
b110 9
b110 %
b110 K
b11 '
b11 ?
b111 &
b111 E
b0 1
1#
#730
0#
#735
b101 C
b1 =
b100 I
b100 7
b101 "
b101 0
b110 &
b110 E
b10 '
b10 ?
b101 %
b101 K
b101 (
b101 9
1#
#740
0#
#745
b11 7
b11 I
b0 =
b100 C
b100 "
b100 0
b100 (
b100 9
b100 %
b100 K
b1 '
b1 ?
b101 &
b101 E
1#
#750
0#
#755
b11 C
b111 =
b10 I
b10 7
b11 "
b11 0
b100 &
b100 E
b0 '
b0 ?
b11 %
b11 K
b11 (
b11 9
1#
#760
0#
#765
b1 7
b1 I
b110 =
b10 C
b10 "
b10 0
b10 (
b10 9
b10 %
b10 K
b111 '
b111 ?
b11 &
b11 E
1#
#770
0#
#775
b1 C
b101 =
b0 I
b0 7
b1 "
b1 0
b10 &
b10 E
b110 '
b110 ?
b1 %
b1 K
b1 (
b1 9
1#
#780
0#
#785
1H
b111 7
b11 I
b100 =
b0 C
b1 2
b0 "
b0 0
b0 (
b0 9
b0 %
b0 K
b101 '
b101 ?
b1 &
b1 E
1#
#790
0#
#795
b10 I
0H
b111 C
b11 =
b110 7
b11 "
b11 0
b1 !
b1 3
b1 1
b0 &
b0 E
b100 '
b100 ?
b11 %
b11 K
b111 (
b111 9
1#
#800
0#
#805
b101 7
b1 I
b10 =
b110 C
b10 "
b10 0
b110 (
b110 9
b10 %
b10 K
b11 '
b11 ?
b111 &
b111 E
1#
#810
0#
#815
b101 C
b1 =
b0 I
b100 7
b1 "
b1 0
b110 &
b110 E
b10 '
b10 ?
b1 %
b1 K
b101 (
b101 9
1#
#820
0#
#825
1<
b11 7
b111 I
b100 =
b100 C
b10 2
b0 "
b0 0
b100 (
b100 9
b0 %
b0 K
b1 '
b1 ?
b101 &
b101 E
1#
